air_flags/__init__.py
air_flags/_version.py
air_flags/config.py
air_flags/flag.py
air_flags/rollout.py
air_flags/utils.py
air_flags/validators.py
airflags-0.1.5.dist-info/LICENSE
airflags-0.1.5.dist-info/METADATA
airflags-0.1.5.dist-info/WHEEL
airflags-0.1.5.dist-info/top_level.txt
airflags-0.1.5.dist-info/RECORD
