Metadata-Version: 2.1
Name: airflags
Version: 0.1.5
Summary: Air flags python library
Home-page: https://github.com/devaway/air-flags-python
Author: devaway
Author-email: airflags@devaway.es
License: BSD
Project-URL: Bug Tracker, https://github.com/devaway/air-flags-python/issues
Platform: UNKNOWN
Classifier: License :: OSI Approved :: BSD License
Classifier: Operating System :: OS Independent
Classifier: Programming Language :: Python :: 3
Classifier: Programming Language :: Python :: 3.4
Classifier: Programming Language :: Python :: 3.5
Classifier: Programming Language :: Python :: 3.6
Classifier: Programming Language :: Python :: 3.7
Classifier: Programming Language :: Python :: 3.8
Classifier: Programming Language :: Python :: 3.9
Requires-Python: >=3.4
License-File: LICENSE
Requires-Dist: pyyaml (==6.0)
Requires-Dist: jsonschema (==4.2.1)
